CalculusOCR/CalculusOCR.py
CalculusOCR/__init__.py
CalculusOCR-0.0.3.dist-info/LICENSE
CalculusOCR-0.0.3.dist-info/METADATA
CalculusOCR-0.0.3.dist-info/WHEEL
CalculusOCR-0.0.3.dist-info/top_level.txt
CalculusOCR-0.0.3.dist-info/RECORD
