Metadata-Version: 2.1
Name: CalculusOCR
Version: 0.0.3
Summary: CalculusOCR: A Vision Transformer that can perform optical character recognition on handwritten calculus expressions and outputs LaTeX code, Sympy equation and solution.
Home-page: https://github.com/JignasP/CalculusOCR/
Author: Jignas Paturu
Author-email: jignas.paturu@hotmail.com
License: MIT
Keywords: artificial intelligence,image to text,calculus
Classifier: Development Status :: 4 - Beta 
Classifier: Intended Audience :: Science/Research
Classifier: Intended Audience :: Developers
Classifier: Topic :: Scientific/Engineering :: Mathematics
Classifier: Topic :: Text Processing :: Markup :: LaTeX
Classifier: License :: OSI Approved :: MIT License
Classifier: Programming Language :: Python
License-File: LICENSE
